jsend/__init__.py
jsend/jsend.py
pyjsend-0.2.2.dist-info/LICENSE
pyjsend-0.2.2.dist-info/METADATA
pyjsend-0.2.2.dist-info/WHEEL
pyjsend-0.2.2.dist-info/top_level.txt
pyjsend-0.2.2.dist-info/RECORD
